.DS_Store
remdex/__init__.py
remdex-0.39.dist-info/LICENSE
remdex-0.39.dist-info/METADATA
remdex-0.39.dist-info/WHEEL
remdex-0.39.dist-info/top_level.txt
remdex-0.39.dist-info/RECORD
