Metadata-Version: 2.1
Name: remdex
Version: 0.39
Summary: Fast and lightweight federated learning framework
Home-page: UNKNOWN
License: MIT
Platform: UNKNOWN
License-File: LICENSE
Requires-Dist: cloudpickle
Requires-Dist: numpy
